distribution_coder/__init__.py
distribution_coder/_distribution_coder.pypy311-pp73-x86_64-linux-gnu.so
distribution_coder/py.typed
distribution_coder-0.1.1.dist-info/METADATA
distribution_coder-0.1.1.dist-info/WHEEL
distribution_coder-0.1.1.dist-info/RECORD
