Metadata-Version: 2.4
Name: distribution-coder
Version: 0.1.1
Requires-Dist: numpy>=1.0
Summary: Fast arithmetic coding over symbol probability distributions in Rust.
Author-email: Paul Morris <ptmorris03@gmail.com>
Requires-Python: >=3.8
